[{
    "2020": {
        "January": [{
                "day": 1,
                "steps": 9581
            },
            {
                "day": 2,
                "steps": 10931
            },
            {
                "day": 3,
                "steps": 3545
            },
            {
                "day": 4,
                "steps": 8178
            },
            {
                "day": 5,
                "steps": 7745
            },
            {
                "day": 6,
                "steps": 11305
            },
            {
                "day": 7,
                "steps": 2753
            },
            {
                "day": 8,
                "steps": 5180
            },
            {
                "day": 9,
                "steps": 11981
            },
            {
                "day": 10,
                "steps": 2838
            },
            {
                "day": 11,
                "steps": 5808
            },
            {
                "day": 12,
                "steps": 3701
            },
            {
                "day": 13,
                "steps": 1895
            },
            {
                "day": 14,
                "steps": 6522
            },
            {
                "day": 15,
                "steps": 3052
            },
            {
                "day": 16,
                "steps": 10114
            },
            {
                "day": 17,
                "steps": 10098
            },
            {
                "day": 18,
                "steps": 10149
            },
            {
                "day": 19,
                "steps": 1656
            },
            {
                "day": 20,
                "steps": 5450
            },
            {
                "day": 21,
                "steps": 10849
            },
            {
                "day": 22,
                "steps": 11178
            },
            {
                "day": 23,
                "steps": 3394
            },
            {
                "day": 24,
                "steps": 9594
            },
            {
                "day": 25,
                "steps": 8974
            },
            {
                "day": 26,
                "steps": 8370
            },
            {
                "day": 27,
                "steps": 11794
            },
            {
                "day": 28,
                "steps": 10316
            },
            {
                "day": 29,
                "steps": 5499
            },
            {
                "day": 30,
                "steps": 2548
            },
            {
                "day": 31,
                "steps": 3937
            }

        ],
        "February": [{
                "day": 1,
                "steps": 2187
            },
            {
                "day": 2,
                "steps": 6258
            },
            {
                "day": 3,
                "steps": 4056
            },
            {
                "day": 4,
                "steps": 3792
            },
            {
                "day": 5,
                "steps": 9388
            },
            {
                "day": 6,
                "steps": 4776
            },
            {
                "day": 7,
                "steps": 6886
            },
            {
                "day": 8,
                "steps": 10639
            },
            {
                "day": 9,
                "steps": 6999
            },
            {
                "day": 10,
                "steps": 1788
            },
            {
                "day": 11,
                "steps": 5104
            },
            {
                "day": 12,
                "steps": 1806
            },
            {
                "day": 13,
                "steps": 11074
            },
            {
                "day": 14,
                "steps": 8404
            },
            {
                "day": 15,
                "steps": 1823
            },
            {
                "day": 16,
                "steps": 5359
            },
            {
                "day": 17,
                "steps": 1326
            },
            {
                "day": 18,
                "steps": 11705
            },
            {
                "day": 19,
                "steps": 5489
            },
            {
                "day": 20,
                "steps": 9054
            },
            {
                "day": 21,
                "steps": 10182
            },
            {
                "day": 22,
                "steps": 6936
            },
            {
                "day": 23,
                "steps": 9548
            },
            {
                "day": 24,
                "steps": 3902
            },
            {
                "day": 25,
                "steps": 11225
            },
            {
                "day": 26,
                "steps": 5253
            },
            {
                "day": 27,
                "steps": 3587
            },
            {
                "day": 28,
                "steps": 10133
            },
            {
                "day": 29,
                "steps": 7255
            }
        ],
        "March": [{
                "day": 1,
                "steps": 9268
            },
            {
                "day": 2,
                "steps": 7700
            },
            {
                "day": 3,
                "steps": 7700
            },
            {
                "day": 4,
                "steps": 6085
            },
            {
                "day": 5,
                "steps": 2169
            },
            {
                "day": 6,
                "steps": 8765
            },
            {
                "day": 7,
                "steps": 1032
            },
            {
                "day": 8,
                "steps": 6447
            },
            {
                "day": 9,
                "steps": 7826
            },
            {
                "day": 10,
                "steps": 3115
            },
            {
                "day": 11,
                "steps": 4395
            },
            {
                "day": 12,
                "steps": 11053
            },
            {
                "day": 13,
                "steps": 11260
            },
            {
                "day": 14,
                "steps": 11260
            },
            {
                "day": 15,
                "steps": 1928
            },
            {
                "day": 16,
                "steps": 9292
            },
            {
                "day": 17,
                "steps": 10927
            },
            {
                "day": 18,
                "steps": 4568
            },
            {
                "day": 19,
                "steps": 2422
            },
            {
                "day": 20,
                "steps": 9581
            },
            {
                "day": 21,
                "steps": 3545
            },
            {
                "day": 22,
                "steps": 7745
            },
            {
                "day": 23,
                "steps": 11305
            },
            {
                "day": 24,
                "steps": 2753
            },
            {
                "day": 25,
                "steps": 11981
            },
            {
                "day": 26,
                "steps": 5808
            },
            {
                "day": 27,
                "steps": 1895
            },
            {
                "day": 28,
                "steps": 3052
            },
            {
                "day": 29,
                "steps": 10114
            },
            {
                "day": 30,
                "steps": 10149
            },
            {
                "day": 31,
                "steps": 5450
            }

        ],
        "April": [{
                "day": 1,
                "steps": 11178
            },
            {
                "day": 2,
                "steps": 9594
            },
            {
                "day": 3,
                "steps": 8370
            },
            {
                "day": 4,
                "steps": 2548
            },
            {
                "day": 5,
                "steps": 6258
            },
            {
                "day": 6,
                "steps": 3792
            },
            {
                "day": 7,
                "steps": 1788
            },
            {
                "day": 8,
                "steps": 11074
            },
            {
                "day": 9,
                "steps": 11705
            },
            {
                "day": 10,
                "steps": 7700
            },
            {
                "day": 11,
                "steps": 2169
            },
            {
                "day": 12,
                "steps": 6447
            },
            {
                "day": 13,
                "steps": 11053
            },
            {
                "day": 14,
                "steps": 11260
            },
            {
                "day": 15,
                "steps": 7797
            },
            {
                "day": 16,
                "steps": 11175
            },
            {
                "day": 17,
                "steps": 7123
            },
            {
                "day": 18,
                "steps": 4601
            },
            {
                "day": 19,
                "steps": 8272
            },
            {
                "day": 20,
                "steps": 5527
            },
            {
                "day": 21,
                "steps": 10976
            },
            {
                "day": 22,
                "steps": 7461
            },
            {
                "day": 23,
                "steps": 11842
            },
            {
                "day": 24,
                "steps": 4307
            },
            {
                "day": 25,
                "steps": 7619
            },
            {
                "day": 26,
                "steps": 12574
            },
            {
                "day": 27,
                "steps": 9930
            },
            {
                "day": 28,
                "steps": 12264
            },
            {
                "day": 29,
                "steps": 11784
            },
            {
                "day": 30,
                "steps": 5914
            }
        ],
        "May": [
            {
                "day": 1,
                "steps": 11510
            },
            {
                "day": 2,
                "steps": 2423
            },
            {
                "day": 3,
                "steps": 12044
            },
            {
                "day": 4,
                "steps": 14623
            },
            {
                "day": 5,
                "steps": 7096
            },
            {
                "day": 6,
                "steps": 14849
            },
            {
                "day": 7,
                "steps": 11798
            },
            {
                "day": 8,
                "steps": 10749
            },
            {
                "day": 9,
                "steps": 1849
            },
            {
                "day": 10,
                "steps": 10325
            },
            {
                "day": 11,
                "steps": 9958
            },
            {
                "day": 12,
                "steps": 4514
            },
            {
                "day": 13,
                "steps": 11823
            },
            {
                "day": 14,
                "steps": 2062
            },
            {
                "day": 15,
                "steps": 13961
            },
            {
                "day": 16,
                "steps": 3206
            },
            {
                "day": 17,
                "steps": 10911
            },
            {
                "day": 18,
                "steps": 6631
            },
            {
                "day": 19,
                "steps": 13865
            },
            {
                "day": 20,
                "steps": 10744
            },
            {
                "day": 21,
                "steps": 13061
            },
            {
                "day": 22,
                "steps": 12157
            },
            {
                "day": 23,
                "steps": 10603
            },
            {
                "day": 24,
                "steps": 6764
            },
            {
                "day": 25,
                "steps": 2627
            },
            {
                "day": 26,
                "steps": 8287
            },
            {
                "day": 27,
                "steps": 8096
            },
            {
                "day": 28,
                "steps": 10668
            },
            {
                "day": 29,
                "steps": 13341
            },
            {
                "day": 30,
                "steps": 11144
            },
            {
                "day": 31,
                "steps": 12163
            }
        ],
        "June": [
            {
                "day": 1,
                "steps": 7151
            },
            {
                "day": 2,
                "steps": 11927
            },
            {
                "day": 3,
                "steps": 11751
            },
            {
                "day": 4,
                "steps": 12984
            },
            {
                "day": 5,
                "steps": 6014
            },
            {
                "day": 6,
                "steps": 13129
            },
            {
                "day": 7,
                "steps": 14304
            },
            {
                "day": 8,
                "steps": 10490
            },
            {
                "day": 9,
                "steps": 13254
            },
            {
                "day": 10,
                "steps": 2172
            },
            {
                "day": 11,
                "steps": 5871
            },
            {
                "day": 12,
                "steps": 10745
            },
            {
                "day": 13,
                "steps": 13024
            },
            {
                "day": 14,
                "steps": 4434
            },
            {
                "day": 15,
                "steps": 10955
            },
            {
                "day": 16,
                "steps": 11016
            },
            {
                "day": 17,
                "steps": 3252
            },
            {
                "day": 18,
                "steps": 14266
            },
            {
                "day": 19,
                "steps": 11703
            },
            {
                "day": 20,
                "steps": 9468
            },
            {
                "day": 21,
                "steps": 13007
            },
            {
                "day": 22,
                "steps": 7031
            },
            {
                "day": 23,
                "steps": 5432
            },
            {
                "day": 24,
                "steps": 9524
            },
            {
                "day": 25,
                "steps": 1770
            },
            {
                "day": 26,
                "steps": 5914
            },
            {
                "day": 27,
                "steps": 11860
            },
            {
                "day": 28,
                "steps": 9898
            },
            {
                "day": 29,
                "steps": 2105
            },
            {
                "day": 30,
                "steps": 6140
            }
        ],
        "July": [
            {
                "day": 1,
                "steps": 3723
            },
            {
                "day": 2,
                "steps": 1332
            },
            {
                "day": 3,
                "steps": 3565
            },
            {
                "day": 4,
                "steps": 6320
            },
            {
                "day": 5,
                "steps": 8806
            },
            {
                "day": 6,
                "steps": 3253
            },
            {
                "day": 7,
                "steps": 12130
            },
            {
                "day": 8,
                "steps": 2958
            },
            {
                "day": 9,
                "steps": 6986
            },
            {
                "day": 10,
                "steps": 12873
            },
            {
                "day": 11,
                "steps": 2411
            },
            {
                "day": 12,
                "steps": 13742
            },
            {
                "day": 13,
                "steps": 7683
            },
            {
                "day": 14,
                "steps": 6406
            },
            {
                "day": 15,
                "steps": 1298
            },
            {
                "day": 16,
                "steps": 5510
            },
            {
                "day": 17,
                "steps": 3943
            },
            {
                "day": 18,
                "steps": 3077
            },
            {
                "day": 19,
                "steps": 1616
            },
            {
                "day": 20,
                "steps": 13099
            },
            {
                "day": 21,
                "steps": 14613
            },
            {
                "day": 22,
                "steps": 14315
            },
            {
                "day": 23,
                "steps": 6270
            },
            {
                "day": 24,
                "steps": 11365
            },
            {
                "day": 25,
                "steps": 1411
            },
            {
                "day": 26,
                "steps": 4921
            },
            {
                "day": 27,
                "steps": 11114
            },
            {
                "day": 28,
                "steps": 12985
            },
            {
                "day": 29,
                "steps": 7353
            },
            {
                "day": 30,
                "steps": 13796
            },
            {
                "day": 31,
                "steps": 10283
            }
        ],
        "August": [
            {
                "day": 1,
                "steps": 1520
            },
            {
                "day": 2,
                "steps": 13754
            },
            {
                "day": 3,
                "steps": 13719
            },
            {
                "day": 4,
                "steps": 1205
            },
            {
                "day": 5,
                "steps": 3585
            },
            {
                "day": 6,
                "steps": 11076
            },
            {
                "day": 7,
                "steps": 12389
            },
            {
                "day": 8,
                "steps": 1773
            },
            {
                "day": 9,
                "steps": 8104
            },
            {
                "day": 10,
                "steps": 9303
            },
            {
                "day": 11,
                "steps": 13817
            },
            {
                "day": 12,
                "steps": 12512
            },
            {
                "day": 13,
                "steps": 11197
            },
            {
                "day": 14,
                "steps": 6998
            },
            {
                "day": 15,
                "steps": 1285
            },
            {
                "day": 16,
                "steps": 1799
            },
            {
                "day": 17,
                "steps": 7996
            },
            {
                "day": 18,
                "steps": 11516
            },
            {
                "day": 19,
                "steps": 3914
            },
            {
                "day": 20,
                "steps": 10285
            },
            {
                "day": 21,
                "steps": 12497
            },
            {
                "day": 22,
                "steps": 9000
            },
            {
                "day": 23,
                "steps": 9362
            },
            {
                "day": 24,
                "steps": 11120
            },
            {
                "day": 25,
                "steps": 4654
            },
            {
                "day": 26,
                "steps": 6953
            },
            {
                "day": 27,
                "steps": 11374
            },
            {
                "day": 28,
                "steps": 11417
            },
            {
                "day": 29,
                "steps": 3752
            },
            {
                "day": 30,
                "steps": 12586
            },
            {
                "day": 31,
                "steps": 3184
            }
        ],
        "September": [
            {
                "day": 1,
                "steps": 5391
            },
            {
                "day": 2,
                "steps": 4311
            },
            {
                "day": 3,
                "steps": 7778
            },
            {
                "day": 4,
                "steps": 8196
            },
            {
                "day": 5,
                "steps": 13443
            },
            {
                "day": 6,
                "steps": 12829
            },
            {
                "day": 7,
                "steps": 12295
            },
            {
                "day": 8,
                "steps": 9944
            },
            {
                "day": 9,
                "steps": 12828
            },
            {
                "day": 10,
                "steps": 1758
            },
            {
                "day": 11,
                "steps": 7472
            },
            {
                "day": 12,
                "steps": 11999
            },
            {
                "day": 13,
                "steps": 10581
            },
            {
                "day": 14,
                "steps": 8570
            },
            {
                "day": 15,
                "steps": 6928
            },
            {
                "day": 16,
                "steps": 5436
            },
            {
                "day": 17,
                "steps": 13953
            },
            {
                "day": 18,
                "steps": 9269
            },
            {
                "day": 19,
                "steps": 7938
            },
            {
                "day": 20,
                "steps": 6841
            },
            {
                "day": 21,
                "steps": 6482
            },
            {
                "day": 22,
                "steps": 9204
            },
            {
                "day": 23,
                "steps": 14415
            },
            {
                "day": 24,
                "steps": 6843
            },
            {
                "day": 25,
                "steps": 11215
            },
            {
                "day": 26,
                "steps": 12734
            },
            {
                "day": 27,
                "steps": 3302
            },
            {
                "day": 28,
                "steps": 6137
            },
            {
                "day": 29,
                "steps": 14401
            },
            {
                "day": 30,
                "steps": 7325
            }
        ],
        "October": [
            {
                "day": 1,
                "steps": 8391
            },
            {
                "day": 2,
                "steps": 4095
            },
            {
                "day": 3,
                "steps": 2694
            },
            {
                "day": 4,
                "steps": 1157
            },
            {
                "day": 5,
                "steps": 3938
            },
            {
                "day": 6,
                "steps": 1594
            },
            {
                "day": 7,
                "steps": 12666
            },
            {
                "day": 8,
                "steps": 10427
            },
            {
                "day": 9,
                "steps": 4660
            },
            {
                "day": 10,
                "steps": 3688
            },
            {
                "day": 11,
                "steps": 11371
            },
            {
                "day": 12,
                "steps": 3802
            },
            {
                "day": 13,
                "steps": 4831
            },
            {
                "day": 14,
                "steps": 3840
            },
            {
                "day": 15,
                "steps": 9476
            },
            {
                "day": 16,
                "steps": 1631
            },
            {
                "day": 17,
                "steps": 6223
            },
            {
                "day": 18,
                "steps": 2632
            },
            {
                "day": 19,
                "steps": 11818
            },
            {
                "day": 20,
                "steps": 10363
            },
            {
                "day": 21,
                "steps": 2983
            },
            {
                "day": 22,
                "steps": 14268
            },
            {
                "day": 23,
                "steps": 9358
            },
            {
                "day": 24,
                "steps": 5327
            },
            {
                "day": 25,
                "steps": 6575
            },
            {
                "day": 26,
                "steps": 13092
            },
            {
                "day": 27,
                "steps": 7843
            },
            {
                "day": 28,
                "steps": 3397
            },
            {
                "day": 29,
                "steps": 8509
            },
            {
                "day": 30,
                "steps": 8295
            },
            {
                "day": 31,
                "steps": 13942
            }
        ],
        "November": [
            {
                "day": 1,
                "steps": 11051
            },
            {
                "day": 2,
                "steps": 12658
            },
            {
                "day": 3,
                "steps": 13708
            },
            {
                "day": 4,
                "steps": 13229
            },
            {
                "day": 5,
                "steps": 4457
            },
            {
                "day": 6,
                "steps": 2757
            },
            {
                "day": 7,
                "steps": 3640
            },
            {
                "day": 8,
                "steps": 8278
            },
            {
                "day": 9,
                "steps": 13000
            },
            {
                "day": 10,
                "steps": 1157
            },
            {
                "day": 11,
                "steps": 13555
            },
            {
                "day": 12,
                "steps": 12761
            },
            {
                "day": 13,
                "steps": 11173
            },
            {
                "day": 14,
                "steps": 3493
            },
            {
                "day": 15,
                "steps": 7221
            },
            {
                "day": 16,
                "steps": 11598
            },
            {
                "day": 17,
                "steps": 7375
            },
            {
                "day": 18,
                "steps": 7931
            },
            {
                "day": 19,
                "steps": 12598
            },
            {
                "day": 20,
                "steps": 3590
            },
            {
                "day": 21,
                "steps": 9623
            },
            {
                "day": 22,
                "steps": 7677
            },
            {
                "day": 23,
                "steps": 3764
            },
            {
                "day": 24,
                "steps": 7563
            },
            {
                "day": 25,
                "steps": 10095
            },
            {
                "day": 26,
                "steps": 8096
            },
            {
                "day": 27,
                "steps": 7596
            },
            {
                "day": 28,
                "steps": 4946
            },
            {
                "day": 29,
                "steps": 8924
            },
            {
                "day": 30,
                "steps": 13016
            }
        ],
        "December": [
            {
                "day": 1,
                "steps": 10293
            },
            {
                "day": 2,
                "steps": 6736
            },
            {
                "day": 3,
                "steps": 14360
            },
            {
                "day": 4,
                "steps": 4595
            },
            {
                "day": 5,
                "steps": 3563
            },
            {
                "day": 6,
                "steps": 7595
            },
            {
                "day": 7,
                "steps": 3557
            },
            {
                "day": 8,
                "steps": 8623
            },
            {
                "day": 9,
                "steps": 1942
            },
            {
                "day": 10,
                "steps": 4120
            },
            {
                "day": 11,
                "steps": 7186
            },
            {
                "day": 12,
                "steps": 8854
            },
            {
                "day": 13,
                "steps": 14033
            },
            {
                "day": 14,
                "steps": 4922
            },
            {
                "day": 15,
                "steps": 1683
            },
            {
                "day": 16,
                "steps": 7888
            },
            {
                "day": 17,
                "steps": 6255
            },
            {
                "day": 18,
                "steps": 8677
            },
            {
                "day": 19,
                "steps": 5313
            },
            {
                "day": 20,
                "steps": 7266
            },
            {
                "day": 21,
                "steps": 7278
            },
            {
                "day": 22,
                "steps": 3375
            },
            {
                "day": 23,
                "steps": 5713
            },
            {
                "day": 24,
                "steps": 7542
            },
            {
                "day": 25,
                "steps": 3083
            },
            {
                "day": 26,
                "steps": 9989
            },
            {
                "day": 27,
                "steps": 6282
            },
            {
                "day": 28,
                "steps": 13983
            },
            {
                "day": 29,
                "steps": 2748
            },
            {
                "day": 30,
                "steps": 3970
            },
            {
                "day": 31,
                "steps": 6274
            }
        ]
    }
}]